urbanopti/__init__.py
urbanopti/greentransport/__init__.py
urbanopti/greentransport/optmodel.py
urbanopti-0.0.2.dist-info/LICENSE
urbanopti-0.0.2.dist-info/METADATA
urbanopti-0.0.2.dist-info/WHEEL
urbanopti-0.0.2.dist-info/top_level.txt
urbanopti-0.0.2.dist-info/RECORD
