Metadata-Version: 2.1
Name: urbanopti
Version: 0.0.2
Summary: engine for the planning of sustainable mobility
Home-page: https://github.com/merraksh/urbanopti
Author: Pietro Belotti
Author-email: pietro.belotti@polimi.it
License: Eclipse Public License v2.0 / Eclipse Distribution License v2.0
Project-URL: Bug Reports, https://github.com/merraksh/urbanopti/issues
Project-URL: Source, https://github.com/merraksh/urbanopti/
Keywords: planning,mobility,green transport
Platform: UNKNOWN
Classifier: Development Status :: 4 - Beta
Classifier: Intended Audience :: Developers
Classifier: Topic :: Software Development :: Build Tools
Classifier: License :: OSI Approved
Classifier: Programming Language :: Python :: 3
Classifier: Programming Language :: Python :: 3.6
Classifier: Programming Language :: Python :: 3.7
Classifier: Programming Language :: Python :: 3.8
Classifier: Programming Language :: Python :: 3.9
Classifier: Programming Language :: Python :: 3.10
Classifier: Programming Language :: Python :: 3 :: Only
Requires-Python: >=3.6, <4
Requires-Dist: mip
Requires-Dist: numpy
Requires-Dist: scipy
